get_code/__init__.py
get_code/main.py
get_code-0.1.0.dist-info/METADATA
get_code-0.1.0.dist-info/WHEEL
get_code-0.1.0.dist-info/RECORD
