Metadata-Version: 2.1
Name: get-code
Version: 0.1.0
Summary: 
Author: Allysson-Christopher
Author-email: 128186654+Allysson-Christopher@users.noreply.github.com
Requires-Python: >=3.13,<4.0
Classifier: Programming Language :: Python :: 3
Requires-Dist: holidays (<1.0)
